{"CceWUgDedU9y/5lMqJhQ0w==":"landscape-nature-clouds-cloudy-2000x767.jpg","2yL1142FJL+CF9cNnyJGmA==":"fotka-2000x1500.jpg","iaRQrMEcNACJeUjKg275mg==":"file-1400x1866.jpg","acYc3CDsIlP+nAApcB9Zuw==":"untitled-384x128.png","N9p1ZMHsLsXmR2UNtbuEFA==":"untitled-160x128.png","bMlwqSZPusyjZQA9kbATlA==":"untitled-160x128.jpg","BVAnW3XU0OpD2xNhTE8NOQ==":"untitled-1-384x128.png","I693rxOTweA1vifn26gB/g==":"lava-and-cherry-blossom-tree-2000x533.png","kncbSr8Pba/0rBGqyWKx0g==":"angel%20del%20collado%202-2000x1333.jpg","6MJ45M0E0q8g0cwKGwQ34Q==":"angel%20del%20collado%20(3)-2000x1333.jpg","rfAr8ZrXEI0plzrOkfJ/1g==":"angel%20del%20collado%20(1)-2000x1333.jpg","aOrNG/hxq560W+2vz3/Agw==":"cd%20rough%20draft%201-2000x1333.jpg","5QyseTu0IJTs7uSE3bGZaQ==":"poster%201-2000x516.jpg","Y95WIdOD2SBMQ8u0Fx9Lnw==":"poster%202-2000x516.jpg","Zd8cO2Dha141EWgbFf8EbA==":"poster%203-2000x516.jpg","T/4xgulOpYhaug2oM//xPA==":"untitled-2000x666.png","k47cSKgn0MeYl9MyK2ngKA==":"poster%20(1)-2000x2962.jpg","81NHEdkHmyEeRMvxez7wug==":"tattoo-2000x2000.jpg","VTQqyBgsb2UG5EjyKGiZfg==":"vw%20logo%20completed-2000x2000.jpg","mMkeEMTUGJLKQ8nrQqhPNQ==":"untitled-265x88.png","AhLvBMAarobic6gSwc8FOA==":"untitled-265x212.png","Ssstz5ZnVTHZwOdPlOVY9g==":"untitled-265x198.png","gMpL3TIPBxPF7IaPXqtS7w==":"file-265x353.jpg","A9RUwxNfwo8Z/Fhhh426DA==":"untitled-1-265x198.png","ftXANIUIaNKCPqV9dBFM9A==":"file_000%20(1)-1400x1866.png","Win8+Ox9LQlJsoAvXWT5Ew==":"path-in-the-red-forest-2000x1280.jpg","aopq56SdACf/jsIg3D+eqw==":"5096072-forest-wallpaper-2000x1125.jpg","ymcutFWxr0wm1DooW6PMdg==":"5096072-forest-wallpaper-2000x1242.jpg","+Y2epMJ6FHfvBIlPtyxPLA==":"large-2000x1332.jpg","dwWRpWXpZdd2woHGrbV/2w==":"angel%20del%20collado-2000x1333.jpg","nYrEqNneBaRgwoTgCOEh0A==":"angel%20del%20collado%20project%2018-2000x2962.jpg","ayInRg0vgB6a6o8LW/Dixg==":"final%20billboard%20poster%201-2000x2962.jpg","paP3hKyfmgbuCtF8Mz7bkA==":"angel%20del%20collado%20(2)-2000x2962.jpg","84BHg7mWZwxNFLPm0vbkOw==":"untitled-170x128.png","JPD/TdgCo83NMdV8T7/ivA==":"file_000%20(1)-1400x1866.jpg","BTX+FCS5RMwa7mO29j0Kng==":"28488-vintage-camera-2000x1336.jpg","zcf8ZQKSBoHuuyNtCqXLlw==":"camera-wallpaper-2000x1250.jpg","249GExb9WNlhLkMprSY2ug==":"camera-wallpaper-1-2000x1250.jpg","RlLoQlJbmdINbLGQG103Uw==":"camera-wallpaper-2-2000x1250.jpg","xPrq31vHMlSJSkVZi/9UNQ==":"camera-wallpaper-3-2000x1250.jpg","GDsY+pnUa0jlBncTu17J0A==":"320a703c419cd48da02907d63370eaac-2000x1332.jpg","H62tkDbGqZ3spv2lIG9sRQ==":"320a703c419cd48da02907d63370eaac-2000x1331.jpg","eXCWXAJYvOjhKJQ/ZVG3uA==":"3-luu-y-khi-mua-ong-kinh-may-anh-cu-2000x1250.jpg","G/cH/0hXUFoo2CqjfjLHlg==":"1659c5fe031950e2240bbf79b78149df-2000x1363.png","bNd//bbYNxm4vlKYs+vCaQ==":"untitled-2000x1353.jpg","TgTGoMWSgk9AhTdoxo0ISg==":"angel%20del%20collado%202-2000x1321.jpg","LrOiHzLUxZfLDKayQNgovQ==":"image%201-2000x1353.jpg","Tbugw5sPk7hOINYMyoU+3Q==":"untitled-1-2000x1353.jpg","cyY/U+GNNQg7hpIbbpOsUg==":"untitled-2-2000x1353.jpg","9Eu7DWPw5NtaIzc+hum6tw==":"angel%20del%20collado%20pre%20drawing-2000x2000.jpg","YXZVLEJe8Hx9+bLhPvJ1hg==":"angel%20del%20collado%20pre%20drawing%201-2000x2000.jpg","aFKo9cA4Iz8phl61XE3KdQ==":"angel%20del%20collado%20pre%20drawing0-2000x788.jpg","i43t8Dx8os6LIVDRc5hNig==":"angel%20del%20collado%20pre%20drawing%201-2000x967.jpg","9tviDvjeU26OLgeqvpn/zw==":"angel%20del%20collado%20pre%20drawing%201-2000x897.jpg","tm38C5cKGjCCEr6+7/SuYQ==":"angel%20del%20collado%20pre%20drawing%202-2000x891.jpg","7mm9hKAshungj8rrPFPOlg==":"lava-and-cherry-blossom-tree-2000x533.jpg","m/l6ytXg1UpTPgq6oQmPXw==":"gallery%20photoshop%202-2000x1330.jpg","+MrqofoxmrbcOxAVjvkp1g==":"gallery%20photoshop-2000x1330.jpg","aU6HT0i+sFA2omh2vAmJ8g==":"gallery%20photoshop%207-2000x1330.jpg","UkOUhcb49sziaiLapNJugg==":"gallery%20photoshop%203-2000x1330.jpg","GcXi4/P0QvoekBHY6hXYcw==":"gallery%20photoshop%204-2000x1330.jpg","e+ndDdpBztKbdN1grS4uag==":"gallery%20photoshop%205-2000x1330.jpg","oP60RdZZWEzJEGtDgNJiiA==":"gallery%20photoshop%209-2000x1330.jpg","bTsDgs+cSlLlKS+WFgdArA==":"gallery%20photoshop%2011-2000x1330.jpg","Jka5xLChb77aMSko7eUOnw==":"lava-and-cherry-blossom-tree-1-2000x533.jpg","3nc2GHJvszWBaPD+s0OsUw==":"angel%20del%20collado%206-2000x1330.jpg","JkF8EtzWdnUyTpQDyFAQYA==":"gallery%20photoshop%2011-2000x1330.jpg","wPb6psanM3H39Yt71jns0g==":"gallery%20photoshop%2012-2000x1330.jpg","QhF4xVfpFZH929ZoY9Woew==":"gallery%20photoshop%2014-2000x1330.jpg","+DVGd0OTiYFw7srodkC0Iw==":"gallery%20photoshop%20115-2000x1330.jpg","FosOV7YvxcxhqJ41qDfevw==":"gallery%20photoshop%2085+-2000x1330.jpg","rUuHra+H0KOinjTO2wzeeQ==":"angel%20del%20collado%20pre%20drawing%204-2000x2000.jpg","2gs/Fv3jBATLlLmyACT0hQ==":"angel%20del%20collado%20pre%20drawing%204-2000x942.jpg","kqgIs3MFTicKGY8m3RS7hw==":"angel%20del%20collado%20pre%20drawing%205-2000x1108.jpg","NGX56+dhRxOqwKAee0Umug==":"angel%20del%20collado%20pre%20drawing%206-2000x1064.jpg","n2duzqhOirRxv+N9juFMkw==":"angel%20del%20collado%20pre%20drawing%207-2000x1166.jpg","tS7aXqbDUMOUvrTk5GWgIA==":"lava-and-cherry-blossom-tree-2-2000x533.jpg","bgELOPGR11hHjZeMyS5F2w==":"angel%20del%20collado%20pre%20drawing%2015-2000x2000.jpg","X05yVDbQjaZcuE69vEVECw==":"angel%20del%20collado%20pre%20drawing%2057-2000x2000.jpg","PintGB+XiAgWL37hOwR69Q==":"angel%20del%20collado%20pre%20drawing%2076-2000x2000.jpg","9ldfSn553F+1ft5LU+0IQg==":"angel%20del%20collado%20pre%20drawing%2057-2000x1115.jpg","BzBpV+c9+4DbPrrwdb0nwQ==":"angel%20del%20collado%20pre%20drawing%2076-2000x1179.jpg","wybwXWlzLnowhd0qKrLMRA==":"angel%20del%20collado%20pre%20drawing%2085-2000x2000.jpg","GsgvPT+A+TXqp86FcWDjQw==":"angel%20del%20collado%20pre%20drawing%20755-2000x2000.jpg","tXmOo86VgBSGvGBNEQDIeQ==":"angel%20del%20collado%20pre%20drawing%206-2000x2000.jpg","wwoFNeUrxsHHurXyxTM5Tg==":"angel%20del%20collado%20pre%20drawing%2021-2000x2000.jpg","QapFOZ0UdyuUJRS4rI3BaQ==":"angel%20del%20collado%20pre%20drawing%2022-2000x2000.jpg","vURSKcuFn/zet6JxlB99Lg==":"angel%20del%20collado%20pre%20drawing%2023-2000x2000.jpg","ovqhImmx0rj2YhhIdGyg5w==":"angel%20del%20collado%20pre%20drawing%2025-2000x2000.jpg","yEO4EYkewwKI9lJmO0HtsA==":"angel%20del%20collado%20pre%20drawing%2026-2000x2000.jpg","yuZT7ojRMkm2QRVR+vP+BA==":"angel%20del%20collado%20pre%20drawing%2027-2000x2000.jpg","AS96LXDzrQjzGYDB3dUwWA==":"angel%20del%20collado%20pre%20drawing%2028-2000x2000.jpg","G6FpqvzQztVIn/biU0zcIw==":"angel%20del%20collado%20pre%20drawing%2029-2000x2000.jpg","HM0hfuqrZZ97+TgHznUZ4w==":"angel%20del%20collado%20pre%20drawing%2030-2000x2000.jpg","pRvOEA5bjwZXeaBW3Ni91A==":"angel%20del%20collado%20pre%20drawing%2031-2000x2000.jpg","x+83Hhc9IMq2newKY6dN6w==":"angel%20del%20collado%20pre%20drawing%2032-2000x2000.jpg","yoc81UEJeAKVKjAUAw1CVA==":"angel%20del%20collado%20pre%20drawing%2042-2000x2000.jpg","N23k0YiNAuUUOWtp1jQjlQ==":"finished%20art-2000x2000.jpg","kj/Tx6BksSqaLGbHRllEig==":"angel%20del%20collado%20pre%20drawing%201-2000x2000.jpg","Zw0m4mgn/lawcBum7bWzxg==":"angel%20del%20collado%20pre%20drawing%202-2000x2000.jpg","/xzIu/D+S102HojXPWOs6w==":"angel%20del%20collado%20pre%20drawing%203-2000x2000.jpg"}